smartdashboard/Experiment_Overview.py
smartdashboard/__init__.py
smartdashboard/__main__.py
smartdashboard/view_builders.py
smartdashboard/views.py
smartdashboard/pages/2_Database_Telemetry.py
smartdashboard/pages/3_Help.py
smartdashboard/pages/__init__.py
smartdashboard/static/SmartSim.png
smartdashboard/static/style.css
smartdashboard/utils/LogReader.py
smartdashboard/utils/ManifestReader.py
smartdashboard/utils/StatusReader.py
smartdashboard/utils/__init__.py
smartdashboard/utils/argparser.py
smartdashboard/utils/errors.py
smartdashboard/utils/helpers.py
smartdashboard/utils/pageSetup.py
smartdashboard/utils/status.py
smartdashboard-0.0.4.dist-info/LICENSE.md
smartdashboard-0.0.4.dist-info/METADATA
smartdashboard-0.0.4.dist-info/WHEEL
smartdashboard-0.0.4.dist-info/entry_points.txt
smartdashboard-0.0.4.dist-info/top_level.txt
smartdashboard-0.0.4.dist-info/RECORD
