Metadata-Version: 2.1
Name: smartdashboard
Version: 0.0.4
Summary: Visualize SmartSim Experiments
Author-email: "CrayLabs: a Hewlett Packard Enterprise OSS Organization" <craylabs@hpe.com>
License: BSD 2-Clause License
Project-URL: Homepage, https://www.craylabs.org
Project-URL: Documentation, https://github.com/CrayLabs/SmartDashboard
Project-URL: Repository, https://github.com/CrayLabs/SmartDashboard
Keywords: scientific,ai,workflow,hpc,analysis
Classifier: Programming Language :: Python :: 3.9
Classifier: Programming Language :: Python :: 3.10
Classifier: Programming Language :: Python :: 3.11
Classifier: License :: OSI Approved :: BSD License
Classifier: Intended Audience :: Science/Research
Classifier: Topic :: Scientific/Engineering
Requires-Python: <3.12,>=3.9
License-File: LICENSE.md
Requires-Dist: altair >=5.2.0
Requires-Dist: pandas >=2.0.0
Requires-Dist: pydantic <2,>=1.10.14
Requires-Dist: streamlit !=1.31.0,!=1.31.1,>=1.28.0
Requires-Dist: watchdog >=3.0.0
Provides-Extra: dev
Requires-Dist: black >=20.8b1 ; extra == 'dev'
Requires-Dist: isort >=5.6.4 ; extra == 'dev'
Requires-Dist: pylint >=2.10.0 ; extra == 'dev'
Requires-Dist: pytest >=6.0.0 ; extra == 'dev'
Requires-Dist: pytest-cov >=2.10.1 ; extra == 'dev'
Requires-Dist: build >=1.0.3 ; extra == 'dev'
Provides-Extra: doc
Requires-Dist: sphinx ==4.4.0 ; extra == 'doc'
Requires-Dist: sphinx-book-theme ==0.2.0 ; extra == 'doc'
Requires-Dist: nbsphinx >=0.8.2 ; extra == 'doc'
Requires-Dist: breathe ==4.31.0 ; extra == 'doc'
Requires-Dist: jinja2 ==3.0.3 ; extra == 'doc'
Provides-Extra: mypy
Requires-Dist: mypy >=1.3.0 ; extra == 'mypy'
Requires-Dist: pandas-stubs ; extra == 'mypy'
Requires-Dist: types-Pillow ; extra == 'mypy'
